LICENSE
README.rst
setup.py
geocode_sparcs/__init__.py
geocode_sparcs/__main__.py
geocode_sparcs/_version.py
geocode_sparcs.egg-info/PKG-INFO
geocode_sparcs.egg-info/SOURCES.txt
geocode_sparcs.egg-info/dependency_links.txt
geocode_sparcs.egg-info/requires.txt
geocode_sparcs.egg-info/top_level.txt