Metadata-Version: 2.1
Name: geocode-sparcs
Version: 0.2.0
Summary: Geocode addresses from New York State's SPARCS data
Home-page: UNKNOWN
Author: Kodi B. Arfer
License: UNKNOWN
Project-URL: Source Code, https://github.com/justlab/geocode_sparcs
Platform: UNKNOWN
Classifier: Programming Language :: Python :: 3
Classifier: License :: OSI Approved :: GNU General Public License v3 or later (GPLv3+)
Classifier: Operating System :: OS Independent
License-File: LICENSE
